sheet2db/__init__.py
sheet2db/main.py
sheet2db_sdk-2.0.2.dist-info/METADATA
sheet2db_sdk-2.0.2.dist-info/WHEEL
sheet2db_sdk-2.0.2.dist-info/top_level.txt
sheet2db_sdk-2.0.2.dist-info/RECORD
