Metadata-Version: 2.4
Name: sheet2db-sdk
Version: 2.0.2
Summary: A python library allows developers to interact with their Google Sheets via the Sheet2DB platform. It provides full CRUD support along with helper utilities for managing sheets.
Home-page: https://sheet2db.io
Author: Sheet2DB
Author-email: support@sheet2db.com
Project-URL: Documentation, https://sheet2db.io/docs/sdk/python
Keywords: sheet2db,google sheets,python,sdk
Requires-Dist: requests
Dynamic: author
Dynamic: author-email
Dynamic: home-page
Dynamic: keywords
Dynamic: project-url
Dynamic: requires-dist
Dynamic: summary
